csvm/__init__.py
csvm/models.py
csvm/reader.py
csvm-0.0.2.dist-info/LICENSE
csvm-0.0.2.dist-info/METADATA
csvm-0.0.2.dist-info/WHEEL
csvm-0.0.2.dist-info/top_level.txt
csvm-0.0.2.dist-info/RECORD
