Metadata-Version: 2.1
Name: csvm
Version: 0.0.2
Author-email: Rafael Sanabria <rafael.d.sanabria@gmail.com>
License: MIT License
Project-URL: Repository, https://github.com/rfsan/csvm
Requires-Python: >=3.8
License-File: LICENSE
Provides-Extra: tests
Requires-Dist: pytest (>=7.4.0) ; extra == 'tests'
